{
  "metadata": {
    "title": "Zonama",
    "utility-menu-id": "utility",
    "primary-menu-id": "primary",
    "footer-menu-1-id": "footer-1",
    "footer-menu-2-id": "footer-2",
    "sub-footer-menu-id": "footer-legal"
  },
  "hero": {
    "image": "/files/zonama-hero.jpg",
    "heading": "Ditch your CMS. There is a new Static Quo.",
    "sub-heading": "Lightning fast Single Page Content Apps. Easy to build, easy to deploy.",
    "actions": [
      {
        "label": "Learn more",
        "uri": "/zonama"
      }
    ]
  },
  "body": "<h1>Static Quo</h1><h2>Lorem Ipsum</h2><p>Class aptent taciti sociosqu ad litora torquent per conubia nostra, per inceptos himenaeos. Duis vitae massa vel ante ultricies bibendum. Curabitur suscipit nulla vitae erat aliquet pulvinar. Quisque condimentum aliquet elementum. Sed suscipit libero sed risus interdum convallis. Vivamus at blandit turpis, ac pretium odio. Morbi ut nulla nisi.</p><h4>Curabitur Malesuada</h4><p>Curabitur malesuada massa nec feugiat egestas. Nullam in mi ac urna tristique tempus. Sed tincidunt risus sem, eget fermentum nulla imperdiet sagittis. Quisque non consequat risus. Morbi eget mattis eros. Nunc eu purus massa. Pellentesque habitant morbi tristique senectus et netus et malesuada fames ac turpis egestas. Phasellus malesuada lectus sit amet varius sagittis.</p><h2>Aliquam</h2><p>Aliquam at posuere lacus. Aliquam erat volutpat. Etiam vulputate ultrices orci, nec maximus libero elementum at. Aliquam et augue sed purus finibus sollicitudin eu in sapien. Phasellus tincidunt metus dui, eget tincidunt tortor luctus sed. Fusce eu lorem lectus. Proin libero tortor, maximus a massa sagittis, volutpat interdum enim. Donec a nisi sed lacus efficitur pretium id nec mauris. Maecenas eget nibh molestie, congue dolor eget, accumsan enim. Aliquam erat volutpat. Donec ultricies magna a sapien sodales, id dapibus quam accumsan. In velit felis, mattis ut metus in, auctor tincidunt ex. Sed nec elementum leo. Suspendisse bibendum massa nec nunc pellentesque blandit. Maecenas tristique purus sit amet lacus pellentesque, eu dapibus nisl aliquam. Fusce justo justo, porttitor et finibus et, dignissim sed erat.</p>",
  "footer-copy": "<h3>Static Quo</h3><p>Lightning fast Single Page Content Apps.</p><p>Ditch your CMS today!</p><p>&nbsp;</p>",
  "copyright": "© 2019- Static Quo / All rights reserved."
}
